[
    {
      "habilitations": [],
      "_id": "5d6218b75bbfa8d08770ecae",
      "code": "612",
      "campus": 1,
      "name": "EDUCAÇÃO ARTÍSTICA",
      "shift": "Diurno",
      "modality": "Presencial"
    },
    {
      "habilitations": [
        5665
      ],
      "_id": "5d6218b75bbfa8d08770ecaf",
      "code": "1023",
      "campus": 1,
      "name": "ARTES VISUAIS",
      "shift": "Noturno",
      "modality": "Presencial"
    },
    {
      "habilitations": [
        1899
      ],
      "_id": "5d6218b75bbfa8d08770ecb0",
      "code": "906",
      "campus": 1,
      "name": "COMPUTAÇÃO",
      "shift": "Noturno",
      "modality": "Presencial"
    },
    {
      "habilitations": [
        5673
      ],
      "_id": "5d6218b75bbfa8d08770ecb1",
      "code": "1422",
      "campus": 1,
      "name": "ARQUITETURA E URBANISMO",
      "shift": "Noturno",
      "modality": "Presencial"
    },
    {
      "habilitations": [
        8117
      ],
      "_id": "5d6218b75bbfa8d08770ecb2",
      "code": "19",
      "campus": 1,
      "name": "ADMINISTRAÇÃO",
      "shift": "Diurno",
      "modality": "Presencial"
    },
    {
      "habilitations": [
        8362
      ],
      "_id": "5d6218b75bbfa8d08770ecb3",
      "code": "1473",
      "campus": 1,
      "name": "COMUNICAÇÃO SOCIAL",
      "shift": "Noturno",
      "modality": "Presencial"
    },
    {
      "habilitations": [
        8591
      ],
      "_id": "5d6218b75bbfa8d08770ecb4",
      "code": "710",
      "campus": 1,
      "name": "CIÊNCIA POLÍTICA",
      "shift": "Diurno",
      "modality": "Presencial"
    },
    {
      "habilitations": [
        2771
      ],
      "_id": "5d6218b75bbfa8d08770ecb5",
      "code": "1538",
      "campus": 1,
      "name": "BIOTECNOLOGIA",
      "shift": "Diurno",
      "modality": "Presencial"
    },
    {
      "habilitations": [
        7315
      ],
      "_id": "5d6218b75bbfa8d08770ecb6",
      "code": "329",
      "campus": 1,
      "name": "EDUCAÇÃO FÍSICA",
      "shift": "Diurno",
      "modality": "Presencial"
    },
    {
      "habilitations": [
        6165
      ],
      "_id": "5d6218b75bbfa8d08770ecb7",
      "code": "86",
      "campus": 1,
      "name": "AGRONOMIA",
      "shift": "Diurno",
      "modality": "Presencial"
    },
    {
      "habilitations": [
        8516
      ],
      "_id": "5d6218b75bbfa8d08770ecb8",
      "code": "507",
      "campus": 1,
      "name": "CIÊNCIAS CONTÁBEIS",
      "shift": "Diurno",
      "modality": "Presencial"
    },
    {
      "habilitations": [
        8486
      ],
      "_id": "5d6218b75bbfa8d08770ecb9",
      "code": "43",
      "campus": 1,
      "name": "DIREITO",
      "shift": "Diurno",
      "modality": "Presencial"
    },
    {
      "habilitations": [
        2216
      ],
      "_id": "5d6218b75bbfa8d08770ecba",
      "code": "94",
      "campus": 1,
      "name": "CIÊNCIAS BIOLÓGICAS",
      "shift": "Diurno",
      "modality": "Presencial"
    },
    {
      "habilitations": [
        1376
      ],
      "_id": "5d6218b75bbfa8d08770ecbb",
      "code": "418",
      "campus": 1,
      "name": "ARTES VISUAIS",
      "shift": "Diurno",
      "modality": "Presencial"
    },
    {
      "habilitations": [
        3221
      ],
      "_id": "5d6218b75bbfa8d08770ecbc",
      "code": "35",
      "campus": 1,
      "name": "CIÊNCIAS ECONÔMICAS",
      "shift": "Diurno",
      "modality": "Presencial"
    },
    {
      "habilitations": [
        60810
      ],
      "_id": "5d6218b75bbfa8d08770ecbd",
      "code": "1589",
      "campus": 1,
      "name": "EDUCAÇÃO FÍSICA",
      "shift": "Diurno",
      "modality": "Presencial"
    },
    {
      "habilitations": [
        5711,
        5371
      ],
      "_id": "5d6218b75bbfa8d08770ecbe",
      "code": "680",
      "campus": 1,
      "name": "ARTES CÊNICAS",
      "shift": "Diurno",
      "modality": "Presencial"
    },
    {
      "habilitations": [
        8222
      ],
      "_id": "5d6218b75bbfa8d08770ecbf",
      "code": "191",
      "campus": 1,
      "name": "BIBLIOTECONOMIA",
      "shift": "Diurno",
      "modality": "Presencial"
    },
    {
      "habilitations": [
        8192
      ],
      "_id": "5d6218b75bbfa8d08770ecc0",
      "code": "728",
      "campus": 1,
      "name": "ARQUIVOLOGIA",
      "shift": "Noturno",
      "modality": "Presencial"
    },
    {
      "habilitations": [
        1856
      ],
      "_id": "5d6218b75bbfa8d08770ecc1",
      "code": "370",
      "campus": 1,
      "name": "CIÊNCIA DA COMPUTAÇÃO",
      "shift": "Diurno",
      "modality": "Presencial"
    },
    {
      "habilitations": [
        7412
      ],
      "_id": "5d6218b75bbfa8d08770ecc2",
      "code": "442",
      "campus": 1,
      "name": "ENFERMAGEM",
      "shift": "Diurno",
      "modality": "Presencial"
    },
    {
      "habilitations": [
        5126
      ],
      "_id": "5d6218b75bbfa8d08770ecc3",
      "code": "27",
      "campus": 1,
      "name": "ARQUITETURA E URBANISMO",
      "shift": "Diurno",
      "modality": "Presencial"
    },
    {
      "habilitations": [
        8150
      ],
      "_id": "5d6218b75bbfa8d08770ecc4",
      "code": "701",
      "campus": 1,
      "name": "ADMINISTRAÇÃO",
      "shift": "Noturno",
      "modality": "Presencial"
    },
    {
      "habilitations": [
        8885
      ],
      "_id": "5d6218b75bbfa8d08770ecc5",
      "code": "817",
      "campus": 1,
      "name": "DIREITO",
      "shift": "Noturno",
      "modality": "Presencial"
    },
    {
      "habilitations": [
        5649
      ],
      "_id": "5d6218b75bbfa8d08770ecc6",
      "code": "671",
      "campus": 1,
      "name": "ARTES VISUAIS",
      "shift": "Diurno",
      "modality": "Presencial"
    },
    {
      "habilitations": [
        2321
      ],
      "_id": "5d6218b75bbfa8d08770ecc7",
      "code": "1333",
      "campus": 1,
      "name": "CIÊNCIAS AMBIENTAIS",
      "shift": "Noturno",
      "modality": "Presencial"
    },
    {
      "habilitations": [
        6254
      ],
      "_id": "5d6218b75bbfa8d08770ecc8",
      "code": "1457",
      "campus": 1,
      "name": "ENGENHARIA AMBIENTAL",
      "shift": "Diurno",
      "modality": "Presencial"
    },
    {
      "habilitations": [
        2259
      ],
      "_id": "5d6218b75bbfa8d08770ecc9",
      "code": "736",
      "campus": 1,
      "name": "CIÊNCIAS BIOLÓGICAS",
      "shift": "Noturno",
      "modality": "Presencial"
    },
    {
      "habilitations": [
        8583
      ],
      "_id": "5d6218b75bbfa8d08770ecca",
      "code": "809",
      "campus": 1,
      "name": "CIÊNCIAS CONTÁBEIS",
      "shift": "Noturno",
      "modality": "Presencial"
    },
    {
      "habilitations": [
        1741
      ],
      "_id": "5d6218b75bbfa8d08770eccb",
      "code": "1341",
      "campus": 1,
      "name": "ENGENHARIA DE COMPUTAÇÃO",
      "shift": "Diurno",
      "modality": "Presencial"
    },
    {
      "habilitations": [
        5380,
        5398
      ],
      "_id": "5d6218b75bbfa8d08770eccc",
      "code": "698",
      "campus": 1,
      "name": "DESIGN",
      "shift": "Diurno",
      "modality": "Presencial"
    },
    {
      "habilitations": [
        6912
      ],
      "_id": "5d6218b75bbfa8d08770eccd",
      "code": "949",
      "campus": 1,
      "name": "ENGENHARIA MECATRÔNICA",
      "shift": "Diurno",
      "modality": "Presencial"
    },
    {
      "habilitations": [
        6521
      ],
      "_id": "5d6218b75bbfa8d08770ecce",
      "code": "396",
      "campus": 1,
      "name": "ENGENHARIA FLORESTAL",
      "shift": "Diurno",
      "modality": "Presencial"
    },
    {
      "habilitations": [
        5720
      ],
      "_id": "5d6218b75bbfa8d08770eccf",
      "code": "1309",
      "campus": 1,
      "name": "ARTES CÊNICAS",
      "shift": "Noturno",
      "modality": "Presencial"
    },
    {
      "habilitations": [
        8354,
        8311,
        8338
      ],
      "_id": "5d6218b75bbfa8d08770ecd0",
      "code": "205",
      "campus": 1,
      "name": "COMUNICAÇÃO SOCIAL",
      "shift": "Diurno",
      "modality": "Presencial"
    },
    {
      "habilitations": [
        1716
      ],
      "_id": "5d6218b75bbfa8d08770ecd1",
      "code": "353",
      "campus": 1,
      "name": "ESTATÍSTICA",
      "shift": "Diurno",
      "modality": "Presencial"
    },
    {
      "habilitations": [
        3352
      ],
      "_id": "5d6218b75bbfa8d08770ecd2",
      "code": "1503",
      "campus": 1,
      "name": "FILOSOFIA",
      "shift": "Noturno",
      "modality": "Presencial"
    },
    {
      "habilitations": [
        1147
      ],
      "_id": "5d6218b75bbfa8d08770ecd3",
      "code": "744",
      "campus": 1,
      "name": "FÍSICA",
      "shift": "Noturno",
      "modality": "Presencial"
    },
    {
      "habilitations": [
        6351
      ],
      "_id": "5d6218b75bbfa8d08770ecd4",
      "code": "892",
      "campus": 1,
      "name": "ENGENHARIA DE REDES DE COMUNICAÇÃO",
      "shift": "Diurno",
      "modality": "Presencial"
    },
    {
      "habilitations": [
        6220
      ],
      "_id": "5d6218b75bbfa8d08770ecd5",
      "code": "582",
      "campus": 1,
      "name": "ENGENHARIA CIVIL",
      "shift": "Diurno",
      "modality": "Presencial"
    },
    {
      "habilitations": [
        7609
      ],
      "_id": "5d6218b75bbfa8d08770ecd6",
      "code": "1449",
      "campus": 1,
      "name": "FARMÁCIA",
      "shift": "Noturno",
      "modality": "Presencial"
    },
    {
      "habilitations": [
        6262
      ],
      "_id": "5d6218b75bbfa8d08770ecd7",
      "code": "1511",
      "campus": 1,
      "name": "GESTÃO DE AGRONEGÓCIOS",
      "shift": "Noturno",
      "modality": "Presencial"
    },
    {
      "habilitations": [
        6017
      ],
      "_id": "5d6218b75bbfa8d08770ecd8",
      "code": "1376",
      "campus": 1,
      "name": "ENGENHARIA DE PRODUÇÃO",
      "shift": "Noturno",
      "modality": "Presencial"
    },
    {
      "habilitations": [
        3417,
        3425
      ],
      "_id": "5d6218b75bbfa8d08770ecd9",
      "code": "230",
      "campus": 1,
      "name": "HISTÓRIA",
      "shift": "Diurno",
      "modality": "Presencial"
    },
    {
      "habilitations": [
        850
      ],
      "_id": "5d6218b75bbfa8d08770ecda",
      "code": "337",
      "campus": 1,
      "name": "JORNALISMO",
      "shift": "Diurno",
      "modality": "Presencial"
    },
    {
      "habilitations": [
        3841,
        3859
      ],
      "_id": "5d6218b75bbfa8d08770ecdb",
      "code": "264",
      "campus": 1,
      "name": "GEOGRAFIA",
      "shift": "Diurno",
      "modality": "Presencial"
    },
    {
      "habilitations": [
        7692
      ],
      "_id": "5d6218b75bbfa8d08770ecdc",
      "code": "876",
      "campus": 1,
      "name": "FARMÁCIA",
      "shift": "Diurno",
      "modality": "Presencial"
    },
    {
      "habilitations": [
        60844
      ],
      "_id": "5d6218b75bbfa8d08770ecdd",
      "code": "1562",
      "campus": 1,
      "name": "ENGENHARIA QUÍMICA",
      "shift": "Diurno",
      "modality": "Presencial"
    },
    {
      "habilitations": [
        4553
      ],
      "_id": "5d6218b75bbfa8d08770ecde",
      "code": "914",
      "campus": 1,
      "name": "LETRAS",
      "shift": "Noturno",
      "modality": "Presencial"
    },
    {
      "habilitations": [
        4146
      ],
      "_id": "5d6218b75bbfa8d08770ecdf",
      "code": "779",
      "campus": 1,
      "name": "LETRAS",
      "shift": "Noturno",
      "modality": "Presencial"
    },
    {
      "habilitations": [
        3131,
        3115,
        3166,
        3123
      ],
      "_id": "5d6218b75bbfa8d08770ece0",
      "code": "213",
      "campus": 1,
      "name": "CIÊNCIAS SOCIAIS",
      "shift": "Diurno",
      "modality": "Presencial"
    },
    {
      "habilitations": [
        6424
      ],
      "_id": "5d6218b75bbfa8d08770ece1",
      "code": "604",
      "campus": 1,
      "name": "ENGENHARIA MECÂNICA",
      "shift": "Diurno",
      "modality": "Presencial"
    },
    {
      "habilitations": [
        1112
      ],
      "_id": "5d6218b75bbfa8d08770ece2",
      "code": "124",
      "campus": 1,
      "name": "FÍSICA",
      "shift": "Diurno",
      "modality": "Presencial"
    },
    {
      "habilitations": [
        8184
      ],
      "_id": "5d6218b75bbfa8d08770ece3",
      "code": "1350",
      "campus": 1,
      "name": "GESTÃO DE POLÍTICAS PÚBLICAS",
      "shift": "Noturno",
      "modality": "Presencial"
    },
    {
      "habilitations": [
        4626
      ],
      "_id": "5d6218b75bbfa8d08770ece4",
      "code": "1414",
      "campus": 1,
      "name": "LETRAS-TRADUÇÃO ESPANHOL",
      "shift": "Noturno",
      "modality": "Presencial"
    },
    {
      "habilitations": [
        6335
      ],
      "_id": "5d6218b75bbfa8d08770ece5",
      "code": "591",
      "campus": 1,
      "name": "ENGENHARIA ELÉTRICA",
      "shift": "Diurno",
      "modality": "Presencial"
    },
    {
      "habilitations": [
        1236
      ],
      "_id": "5d6218b75bbfa8d08770ece6",
      "code": "1384",
      "campus": 1,
      "name": "GEOFÍSICA",
      "shift": "Diurno",
      "modality": "Presencial"
    },
    {
      "habilitations": [
        4090
      ],
      "_id": "5d6218b75bbfa8d08770ece7",
      "code": "1465",
      "campus": 1,
      "name": "LÍNGUAS ESTRANGEIRAS APLICADAS - MSI",
      "shift": "Diurno",
      "modality": "Presencial"
    },
    {
      "habilitations": [
        3336,
        3344
      ],
      "_id": "5d6218b75bbfa8d08770ece8",
      "code": "221",
      "campus": 1,
      "name": "FILOSOFIA",
      "shift": "Diurno",
      "modality": "Presencial"
    },
    {
      "habilitations": [
        3476
      ],
      "_id": "5d6218b75bbfa8d08770ece9",
      "code": "1392",
      "campus": 1,
      "name": "HISTÓRIA",
      "shift": "Noturno",
      "modality": "Presencial"
    },
    {
      "habilitations": [
        1228
      ],
      "_id": "5d6218b75bbfa8d08770ecea",
      "code": "132",
      "campus": 1,
      "name": "GEOLOGIA",
      "shift": "Diurno",
      "modality": "Presencial"
    },
    {
      "habilitations": [
        1368
      ],
      "_id": "5d6218b75bbfa8d08770eceb",
      "code": "752",
      "campus": 1,
      "name": "MATEMÁTICA",
      "shift": "Noturno",
      "modality": "Presencial"
    },
    {
      "habilitations": [
        6181
      ],
      "_id": "5d6218b75bbfa8d08770ecec",
      "code": "884",
      "campus": 1,
      "name": "MEDICINA VETERINÁRIA",
      "shift": "Diurno",
      "modality": "Presencial"
    },
    {
      "habilitations": [
        5606
      ],
      "_id": "5d6218b75bbfa8d08770eced",
      "code": "1406",
      "campus": 1,
      "name": "MÚSICA",
      "shift": "Noturno",
      "modality": "Presencial"
    },
    {
      "habilitations": [
        9245
      ],
      "_id": "5d6218b75bbfa8d08770ecee",
      "code": "787",
      "campus": 1,
      "name": "PEDAGOGIA",
      "shift": "Noturno",
      "modality": "Presencial"
    },
    {
      "habilitations": [
        7218
      ],
      "_id": "5d6218b75bbfa8d08770ecef",
      "code": "647",
      "campus": 1,
      "name": "ODONTOLOGIA",
      "shift": "Diurno",
      "modality": "Presencial"
    },
    {
      "habilitations": [
        1449
      ],
      "_id": "5d6218b75bbfa8d08770ecf0",
      "code": "167",
      "campus": 1,
      "name": "QUÍMICA",
      "shift": "Diurno",
      "modality": "Presencial"
    },
    {
      "habilitations": [
        698
      ],
      "_id": "5d6218b85bbfa8d08770ecf1",
      "code": "345",
      "campus": 1,
      "name": "LÍNGUA DE SINAIS BRASILEIRA/PORTUGUÊS COMO SEGUNDA LÍNGUA",
      "shift": "Diurno",
      "modality": "Presencial"
    },
    {
      "habilitations": [
        4154
      ],
      "_id": "5d6218b85bbfa8d08770ecf2",
      "code": "825",
      "campus": 1,
      "name": "LETRAS",
      "shift": "Noturno",
      "modality": "Presencial"
    },
    {
      "habilitations": [
        1589
      ],
      "_id": "5d6218b85bbfa8d08770ecf3",
      "code": "1481",
      "campus": 1,
      "name": "QUÍMICA TECNOLÓGICA",
      "shift": "Diurno",
      "modality": "Presencial"
    },
    {
      "habilitations": [
        4529,
        4511
      ],
      "_id": "5d6218b85bbfa8d08770ecf4",
      "code": "639",
      "campus": 1,
      "name": "LETRAS-TRADUÇÃO",
      "shift": "Diurno",
      "modality": "Presencial"
    },
    {
      "habilitations": [
        7161
      ],
      "_id": "5d6218b85bbfa8d08770ecf5",
      "code": "1431",
      "campus": 1,
      "name": "SAÚDE COLETIVA",
      "shift": "Noturno",
      "modality": "Presencial"
    },
    {
      "habilitations": [
        6271
      ],
      "_id": "5d6218b85bbfa8d08770ecf6",
      "code": "1520",
      "campus": 1,
      "name": "TURISMO",
      "shift": "Diurno",
      "modality": "Presencial"
    },
    {
      "habilitations": [
        7111
      ],
      "_id": "5d6218b85bbfa8d08770ecf7",
      "code": "159",
      "campus": 1,
      "name": "MEDICINA",
      "shift": "Diurno",
      "modality": "Presencial"
    },
    {
      "habilitations": [
        3522
      ],
      "_id": "5d6218b85bbfa8d08770ecf8",
      "code": "1490",
      "campus": 1,
      "name": "SERVIÇO SOCIAL",
      "shift": "Noturno",
      "modality": "Presencial"
    },
    {
      "habilitations": [
        8265
      ],
      "_id": "5d6218b85bbfa8d08770ecf9",
      "code": "1368",
      "campus": 1,
      "name": "MUSEOLOGIA",
      "shift": "Diurno",
      "modality": "Presencial"
    },
    {
      "habilitations": [
        1325,
        1341
      ],
      "_id": "5d6218b85bbfa8d08770ecfa",
      "code": "141",
      "campus": 1,
      "name": "MATEMÁTICA",
      "shift": "Diurno",
      "modality": "Presencial"
    },
    {
      "habilitations": [
        7510
      ],
      "_id": "5d6218b85bbfa8d08770ecfb",
      "code": "451",
      "campus": 1,
      "name": "NUTRIÇÃO",
      "shift": "Diurno",
      "modality": "Presencial"
    },
    {
      "habilitations": [
        7323
      ],
      "_id": "5d6218b85bbfa8d08770ecfc",
      "code": "1163",
      "campus": 1,
      "name": "EDUCAÇÃO FÍSICA",
      "shift": "Diurno",
      "modality": "Distância"
    },
    {
      "habilitations": [
        1503
      ],
      "_id": "5d6218b85bbfa8d08770ecfd",
      "code": "761",
      "campus": 1,
      "name": "QUÍMICA",
      "shift": "Noturno",
      "modality": "Presencial"
    },
    {
      "habilitations": [
        9229
      ],
      "_id": "5d6218b85bbfa8d08770ecfe",
      "code": "60",
      "campus": 1,
      "name": "PEDAGOGIA",
      "shift": "Diurno",
      "modality": "Presencial"
    },
    {
      "habilitations": [
        4910
      ],
      "_id": "5d6218b85bbfa8d08770ecff",
      "code": "1147",
      "campus": 1,
      "name": "LETRAS",
      "shift": "Diurno",
      "modality": "Distância"
    },
    {
      "habilitations": [
        3727
      ],
      "_id": "5d6218b85bbfa8d08770ed00",
      "code": "400",
      "campus": 1,
      "name": "RELAÇÕES INTERNACIONAIS",
      "shift": "Diurno",
      "modality": "Presencial"
    },
    {
      "habilitations": [
        2313
      ],
      "_id": "5d6218b85bbfa8d08770ed01",
      "code": "1325",
      "campus": 1,
      "name": "CIÊNCIAS BIOLÓGICAS",
      "shift": "Diurno",
      "modality": "Distância"
    },
    {
      "habilitations": [
        9296
      ],
      "_id": "5d6218b85bbfa8d08770ed02",
      "code": "1180",
      "campus": 1,
      "name": "PEDAGOGIA",
      "shift": "Diurno",
      "modality": "Distância"
    },
    {
      "habilitations": [
        3514
      ],
      "_id": "5d6218b85bbfa8d08770ed03",
      "code": "272",
      "campus": 1,
      "name": "SERVIÇO SOCIAL",
      "shift": "Diurno",
      "modality": "Presencial"
    },
    {
      "habilitations": [
        60828
      ],
      "_id": "5d6218b85bbfa8d08770ed04",
      "code": "1554",
      "campus": 1,
      "name": "TEORIA, CRÍTICA E HISTÓRIA DA ARTE",
      "shift": "Noturno",
      "modality": "Presencial"
    },
    {
      "habilitations": [
        5509
      ],
      "_id": "5d6218b85bbfa8d08770ed05",
      "code": "1139",
      "campus": 1,
      "name": "MÚSICA",
      "shift": "Diurno",
      "modality": "Distância"
    },
    {
      "habilitations": [
        3867
      ],
      "_id": "5d6218b85bbfa8d08770ed06",
      "code": "1317",
      "campus": 1,
      "name": "GEOGRAFIA",
      "shift": "Diurno",
      "modality": "Distância"
    },
    {
      "habilitations": [
        2712,
        2721,
        2739
      ],
      "_id": "5d6218b85bbfa8d08770ed07",
      "code": "183",
      "campus": 1,
      "name": "PSICOLOGIA",
      "shift": "Diurno",
      "modality": "Presencial"
    },
    {
      "habilitations": [
        5151
      ],
      "_id": "5d6218b85bbfa8d08770ed08",
      "code": "1171",
      "campus": 1,
      "name": "TEATRO",
      "shift": "Diurno",
      "modality": "Distância"
    },
    {
      "habilitations": [
        4219,
        4227,
        4316,
        4324,
        4111,
        4120,
        4430
      ],
      "_id": "5d6218b85bbfa8d08770ed09",
      "code": "51",
      "campus": 1,
      "name": "LETRAS",
      "shift": "Diurno",
      "modality": "Presencial"
    },
    {
      "habilitations": [
        5223,
        5541,
        5614,
        5266,
        5576,
        5584,
        5550,
        5592,
        5622,
        5274,
        5631,
        5568,
        5258,
        5525,
        5282,
        5517,
        5533
      ],
      "_id": "5d6218b85bbfa8d08770ed0a",
      "code": "175",
      "campus": 1,
      "name": "MÚSICA",
      "shift": "Diurno",
      "modality": "Presencial"
    },
    {
      "habilitations": [
        434
      ],
      "_id": "5d6218b85bbfa8d08770ed0b",
      "code": "281",
      "campus": 1,
      "name": "MÚSICA",
      "shift": "Diurno",
      "modality": "Presencial"
    },
    {
      "habilitations": [
        6157
      ],
      "_id": "5d6218b85bbfa8d08770ed0c",
      "code": "1287",
      "campus": 2,
      "name": "GESTÃO AMBIENTAL",
      "shift": "Noturno",
      "modality": "Presencial"
    },
    {
      "habilitations": [
        6190
      ],
      "_id": "5d6218b85bbfa8d08770ed0d",
      "code": "1091",
      "campus": 2,
      "name": "GESTÃO DO AGRONEGÓCIO",
      "shift": "Diurno",
      "modality": "Presencial"
    },
    {
      "habilitations": [
        2283
      ],
      "_id": "5d6218b85bbfa8d08770ed0e",
      "code": "1104",
      "campus": 2,
      "name": "CIÊNCIAS NATURAIS",
      "shift": "Diurno",
      "modality": "Presencial"
    },
    {
      "habilitations": [
        2291
      ],
      "_id": "5d6218b85bbfa8d08770ed0f",
      "code": "1295",
      "campus": 2,
      "name": "CIÊNCIAS NATURAIS",
      "shift": "Noturno",
      "modality": "Presencial"
    },
    {
      "habilitations": [
        9636,
        9628,
        761
      ],
      "_id": "5d6218b85bbfa8d08770ed10",
      "code": "1121",
      "campus": 2,
      "name": "EDUCAÇÃO DO CAMPO",
      "shift": "Diurno",
      "modality": "Presencial"
    },
    {
      "habilitations": [
        60852
      ],
      "_id": "5d6218b85bbfa8d08770ed11",
      "code": "1571",
      "campus": 3,
      "name": "FONOAUDIOLOGIA",
      "shift": "Diurno",
      "modality": "Presencial"
    },
    {
      "habilitations": [
        7072
      ],
      "_id": "5d6218b85bbfa8d08770ed12",
      "code": "1244",
      "campus": 3,
      "name": "ENFERMAGEM",
      "shift": "Diurno",
      "modality": "Presencial"
    },
    {
      "habilitations": [
        7137
      ],
      "_id": "5d6218b85bbfa8d08770ed13",
      "code": "1252",
      "campus": 3,
      "name": "FISIOTERAPIA",
      "shift": "Diurno",
      "modality": "Presencial"
    },
    {
      "habilitations": [
        7145
      ],
      "_id": "5d6218b85bbfa8d08770ed14",
      "code": "1261",
      "campus": 3,
      "name": "TERAPIA OCUPACIONAL",
      "shift": "Diurno",
      "modality": "Presencial"
    },
    {
      "habilitations": [
        7153
      ],
      "_id": "5d6218b85bbfa8d08770ed15",
      "code": "1279",
      "campus": 3,
      "name": "SAÚDE COLETIVA",
      "shift": "Diurno",
      "modality": "Presencial"
    },
    {
      "habilitations": [
        7013
      ],
      "_id": "5d6218b85bbfa8d08770ed16",
      "code": "1236",
      "campus": 3,
      "name": "FARMÁCIA",
      "shift": "Diurno",
      "modality": "Presencial"
    },
    {
      "habilitations": [
        6131
      ],
      "_id": "5d6218b85bbfa8d08770ed17",
      "code": "1601",
      "campus": 4,
      "name": "ENGENHARIA ELETRÔNICA",
      "shift": "Diurno",
      "modality": "Presencial"
    },
    {
      "habilitations": [
        6009
      ],
      "_id": "5d6218b85bbfa8d08770ed18",
      "code": "1228",
      "campus": 4,
      "name": "ENGENHARIA",
      "shift": "Diurno",
      "modality": "Presencial"
    },
    {
      "habilitations": [
        60836
      ],
      "_id": "5d6218b85bbfa8d08770ed19",
      "code": "1643",
      "campus": 4,
      "name": "ENGENHARIA AEROESPACIAL",
      "shift": "Diurno",
      "modality": "Presencial"
    },
    {
      "habilitations": [
        6297
      ],
      "_id": "5d6218b85bbfa8d08770ed1a",
      "code": "1627",
      "campus": 4,
      "name": "ENGENHARIA AUTOMOTIVA",
      "shift": "Diurno",
      "modality": "Presencial"
    },
    {
      "habilitations": [
        6360
      ],
      "_id": "5d6218b85bbfa8d08770ed1b",
      "code": "1635",
      "campus": 4,
      "name": "ENGENHARIA DE SOFTWARE",
      "shift": "Diurno",
      "modality": "Presencial"
    },
    {
      "habilitations": [
        6289
      ],
      "_id": "5d6218b85bbfa8d08770ed1c",
      "code": "1619",
      "campus": 4,
      "name": "ENGENHARIA DE ENERGIA",
      "shift": "Diurno",
      "modality": "Presencial"
    }
  ]